MarkovPoemModule
