Metadata-Version: 1.2
Name: MarkovPoemModule
Version: 1.4.7
Summary: A poetry generator, based on the text generator on the Markov chains (MarkovTextGenerator).
Home-page: https://github.com/NyashniyVladya/PoemModule
Author: Vladya
Author-email: UNKNOWN
License: UNKNOWN
Keywords: vladya markovgenerator markov_generator MarkovPoemModule markov_chain poem_module poem_generator poem
Platform: UNKNOWN
Classifier: Programming Language :: Python :: 3.6
Requires-Python: >=3.6
